odoo/addons/l10n_es_atc_mod425/README.rst
odoo/addons/l10n_es_atc_mod425/__init__.py
odoo/addons/l10n_es_atc_mod425/__manifest__.py
odoo/addons/l10n_es_atc_mod425/data/l10n.es.aeat.map.tax.csv
odoo/addons/l10n_es_atc_mod425/data/l10n.es.aeat.map.tax.line.account.csv
odoo/addons/l10n_es_atc_mod425/data/l10n.es.aeat.map.tax.line.csv
odoo/addons/l10n_es_atc_mod425/data/l10n.es.aeat.map.tax.line.tax.csv
odoo/addons/l10n_es_atc_mod425/i18n/l10n_es_atc_mod425.pot
odoo/addons/l10n_es_atc_mod425/models/__init__.py
odoo/addons/l10n_es_atc_mod425/models/mod425.py
odoo/addons/l10n_es_atc_mod425/readme/CONTRIBUTORS.md
odoo/addons/l10n_es_atc_mod425/readme/DESCRIPTION.md
odoo/addons/l10n_es_atc_mod425/readme/INSTALL.md
odoo/addons/l10n_es_atc_mod425/readme/ROADMAP.md
odoo/addons/l10n_es_atc_mod425/readme/USAGE.md
odoo/addons/l10n_es_atc_mod425/reports/Presentacion-425-XMLSchema.xsd
odoo/addons/l10n_es_atc_mod425/reports/mod425_report.xml
odoo/addons/l10n_es_atc_mod425/security/ir.model.access.csv
odoo/addons/l10n_es_atc_mod425/security/l10n_es_atc_mod425_security.xml
odoo/addons/l10n_es_atc_mod425/static/description/icon.png
odoo/addons/l10n_es_atc_mod425/static/description/index.html
odoo/addons/l10n_es_atc_mod425/static/src/pdf/caratula_sobre_425.pdf
odoo/addons/l10n_es_atc_mod425/tests/__init__.py
odoo/addons/l10n_es_atc_mod425/tests/test_l10n_es_atc_mod425.py
odoo/addons/l10n_es_atc_mod425/views/mod425_view.xml
odoo_addon_l10n_es_atc_mod425-17.0.1.0.1.dist-info/METADATA
odoo_addon_l10n_es_atc_mod425-17.0.1.0.1.dist-info/WHEEL
odoo_addon_l10n_es_atc_mod425-17.0.1.0.1.dist-info/top_level.txt
odoo_addon_l10n_es_atc_mod425-17.0.1.0.1.dist-info/RECORD
