Metadata-Version: 2.1
Name: odoo-addon-l10n_es_atc_mod425
Version: 17.0.1.0.1
Requires-Python: >=3.10
Requires-Dist: odoo-addon-l10n_es_atc>=17.0dev,<17.1dev
Requires-Dist: odoo-addon-l10n_es_igic>=17.0dev,<17.1dev
Requires-Dist: odoo>=17.0a,<17.1dev
Summary: ATC Modelo 425
Home-page: https://github.com/OCA/l10n-spain
License: AGPL-3
Author: Tecnativa,Binhex System Solutions,Odoo Community Association (OCA)
Author-email: support@odoo-community.org
Classifier: Programming Language :: Python
Classifier: Framework :: Odoo
Classifier: Framework :: Odoo :: 17.0
Classifier: License :: OSI Approved :: GNU Affero General Public License v3
